README.md
setup.cfg
setup.py
sudsoln/__init__.py
sudsoln/candidate.py
sudsoln/formatting.py
sudsoln/questions.py
sudsoln/sarray.py
sudsoln/sudoku.py
sudsoln/tests.py
sudsoln.egg-info/PKG-INFO
sudsoln.egg-info/SOURCES.txt
sudsoln.egg-info/dependency_links.txt
sudsoln.egg-info/top_level.txt