Metadata-Version: 2.1
Name: sudsoln
Version: 0.1.0
Summary: A n ** 2-by-n ** 2 sudoku solver.
Home-page: https://github.com/joon3216/sudsoln
Author: Junkyu Park
Author-email: joon3216@gmail.com
License: MIT License
Platform: UNKNOWN
Classifier: Development Status :: 3 - Alpha
Classifier: Programming Language :: Python :: 3
Classifier: License :: OSI Approved :: MIT License
Classifier: Operating System :: OS Independent
Requires-Python: >=3
